relyapi/__init__.py
relyapi/client.py
relyapi/invoke.py
relyapi/plugin.py
relyapi/transport.py
relyapi/utils.py
relyapi-0.1.9.dist-info/METADATA
relyapi-0.1.9.dist-info/WHEEL
relyapi-0.1.9.dist-info/RECORD
