Metadata-Version: 2.3
Name: relyapi
Version: 0.1.9
Summary: 
Author: fovegage
Author-email: fovegage@gmail.com
Requires-Python: >=3.10,<3.15
Classifier: Programming Language :: Python :: 3
Classifier: Programming Language :: Python :: 3.10
Classifier: Programming Language :: Python :: 3.11
Classifier: Programming Language :: Python :: 3.12
Classifier: Programming Language :: Python :: 3.13
Requires-Dist: httpx (>=0.28.1,<0.29.0)
Requires-Dist: tenacity (>=9.1.2,<10.0.0)
